AUTHORS.txt
CHANGES.txt
LICENSE.txt
MANIFEST.in
README.rst
setup.py
django_qbe/__init__.py
django_qbe/exports.py
django_qbe/forms.py
django_qbe/operators.py
django_qbe/settings.py
django_qbe/urls.py
django_qbe/utils.py
django_qbe/views.py
django_qbe/widgets.py
django_qbe.egg-info/PKG-INFO
django_qbe.egg-info/SOURCES.txt
django_qbe.egg-info/dependency_links.txt
django_qbe.egg-info/not-zip-safe
django_qbe.egg-info/requires.txt
django_qbe.egg-info/top_level.txt
django_qbe/locale/en/LC_MESSAGES/django.po
django_qbe/locale/fr_CA/LC_MESSAGES/django.mo
django_qbe/locale/fr_CA/LC_MESSAGES/django.po
django_qbe/savedqueries/__init__.py
django_qbe/savedqueries/admin.py
django_qbe/savedqueries/apps.py
django_qbe/savedqueries/models.py
django_qbe/savedqueries/management/__init__.py
django_qbe/savedqueries/management/commands/__init__.py
django_qbe/savedqueries/management/commands/qbe_export.py
django_qbe/savedqueries/migrations/0001_initial.py
django_qbe/savedqueries/migrations/__init__.py
django_qbe/static/django_qbe/css/qbe.css
django_qbe/static/django_qbe/css/wireit.css
django_qbe/static/django_qbe/img/close.png
django_qbe/static/django_qbe/img/cut.png
django_qbe/static/django_qbe/img/grid.jpg
django_qbe/static/django_qbe/img/key.gif
django_qbe/static/django_qbe/img/right_arrow.gif
django_qbe/static/django_qbe/img/right_arrow_red.gif
django_qbe/static/django_qbe/img/terminals.png
django_qbe/static/django_qbe/img/terminals2.png
django_qbe/static/django_qbe/img/terminals3.png
django_qbe/static/django_qbe/js/excanvas.js
django_qbe/static/django_qbe/js/jquery.formset.js
django_qbe/static/django_qbe/js/jquery.js
django_qbe/static/django_qbe/js/jquery.jsplumb.js
django_qbe/static/django_qbe/js/jquery.ui.js
django_qbe/static/django_qbe/js/qbe.core.js
django_qbe/static/django_qbe/js/qbe.diagram.js
django_qbe/templates/qbe.html
django_qbe/templates/qbe.js
django_qbe/templates/qbe_index.html
django_qbe/templates/qbe_index.js
django_qbe/templates/qbe_results.html
django_qbe/templates/admin/savedqueries/savedquery/change_form.html
django_qbe/templatetags/__init__.py
django_qbe/templatetags/qbe_tags.py