Metadata-Version: 1.1
Name: django-qbe
Version: 0.3.0
Summary: Django admin tool for custom reports
Home-page: http://versae.github.com/qbe/
Author: Javier de la Rosa
Author-email: versae@gmail.com
License: MIT
Keywords: qbe django admin reports query sql
Platform: UNKNOWN
Classifier: Development Status :: 4 - Beta
Classifier: Framework :: Django
Classifier: Intended Audience :: Developers
Classifier: License :: OSI Approved :: MIT License
Classifier: Operating System :: OS Independent
Classifier: Programming Language :: JavaScript
Classifier: Programming Language :: Python
Classifier: Topic :: Internet :: WWW/HTTP
